ssb_libtest9/__init__.py
ssb_libtest9/__main__.py
ssb_libtest9/functions.py
ssb_libtest9/py.typed
ssb_libtest9-0.0.2.dist-info/LICENSE
ssb_libtest9-0.0.2.dist-info/METADATA
ssb_libtest9-0.0.2.dist-info/WHEEL
ssb_libtest9-0.0.2.dist-info/entry_points.txt
ssb_libtest9-0.0.2.dist-info/RECORD
